empyrealSDK/__init__.py
empyrealSDK/exc.py
empyrealSDK/sdk.py
empyrealSDK/modules/__init__.py
empyrealSDK/modules/core/__init__.py
empyrealSDK/modules/core/application.py
empyrealSDK/modules/core/infra.py
empyrealSDK/modules/core/token.py
empyrealSDK/modules/core/user.py
empyrealSDK/modules/core/vault.py
empyrealSDK/modules/core/wallet.py
empyrealSDK/modules/dex/__init__.py
empyrealSDK/modules/dex/price.py
empyrealSDK/modules/dex/swap.py
empyrealSDK/types/__init__.py
empyrealSDK/types/application.py
empyrealSDK/types/dex.py
empyrealSDK/types/network.py
empyrealSDK/types/security.py
empyrealSDK/types/token.py
empyrealSDK/types/transaction.py
empyrealSDK/types/user.py
empyrealSDK/types/vault.py
empyrealSDK/types/wallet.py
empyrealSDK/utils/__init__.py
empyrealSDK/utils/client.py
empyrealSDK/utils/request_helpers.py
empyrealSDK-0.0.1.post14.dist-info/LICENSE.txt
empyrealSDK-0.0.1.post14.dist-info/METADATA
empyrealSDK-0.0.1.post14.dist-info/WHEEL
empyrealSDK-0.0.1.post14.dist-info/top_level.txt
empyrealSDK-0.0.1.post14.dist-info/RECORD
